zeolite/__init__.py
zeolite/py.typed
zeolite/_utils/__init__.py
zeolite/_utils/args.py
zeolite/_utils/calc_age.py
zeolite/_utils/column_id.py
zeolite/_utils/data_type.py
zeolite/_utils/financial_years.py
zeolite/_utils/parse_dates.py
zeolite/_utils/sanitise.py
zeolite/column/__init__.py
zeolite/column/_base/__init__.py
zeolite/column/_clean/__init__.py
zeolite/column/_clean/_base.py
zeolite/column/_clean/_boolean.py
zeolite/column/_clean/_custom.py
zeolite/column/_clean/_date.py
zeolite/column/_clean/_enum.py
zeolite/column/_clean/_id.py
zeolite/column/_clean/_number.py
zeolite/column/_clean/_string.py
zeolite/column/validation/__init__.py
zeolite/column/validation/_base.py
zeolite/column/validation/_utils/__init__.py
zeolite/column/validation/_utils/data_checks.py
zeolite/column/validation/_utils/range.py
zeolite/column/validation/_utils/types.py
zeolite/column/validation/_utils/validation_node.py
zeolite/column/validation/variants/__init__.py
zeolite/column/validation/variants/_custom.py
zeolite/column/validation/variants/_date.py
zeolite/column/validation/variants/_equality.py
zeolite/column/validation/variants/_in_list.py
zeolite/column/validation/variants/_null.py
zeolite/column/validation/variants/_number.py
zeolite/column/validation/variants/_string.py
zeolite/column/validation/variants/_unique.py
zeolite/exceptions/__init__.py
zeolite/ref/__init__.py
zeolite/ref/_reference.py
zeolite/registry/__init__.py
zeolite/registry/lineage.py
zeolite/registry/optimise_calc_stages.py
zeolite/registry/verify_registry.py
zeolite/schema/__init__.py
zeolite/schema/_table.py
zeolite/schema/_utils/__init__.py
zeolite/schema/_utils/coerce_types.py
zeolite/schema/_utils/normalise.py
zeolite/schema/_utils/prepare_dataset.py
zeolite/schema/validation/__init__.py
zeolite/schema/validation/_base.py
zeolite/schema/validation/variants/__init__.py
zeolite/schema/validation/variants/_min_rows.py
zeolite/schema/validation/variants/_removed_rows.py
zeolite/types/__init__.py
zeolite-0.2.2.dist-info/METADATA
zeolite-0.2.2.dist-info/WHEEL
zeolite-0.2.2.dist-info/RECORD
