Metadata-Version: 2.4
Name: zeolite
Version: 0.2.2
Summary: A library to process raw data into a structured format
Requires-Python: >=3.12
Requires-Dist: polars>=1.34.0
Provides-Extra: dev
Requires-Dist: pytest-cov>=7.0.0; extra == 'dev'
Requires-Dist: pytest>=8.4.2; extra == 'dev'
Requires-Dist: ruff>=0.14.2; extra == 'dev'
